alacorder/__init__.py
alacorder/__main__.py
alacorder/alac.py
alacorder/template.docx
alacorder/tui.tcss
alacorder-81.2.26.dist-info/LICENSE
alacorder-81.2.26.dist-info/METADATA
alacorder-81.2.26.dist-info/WHEEL
alacorder-81.2.26.dist-info/entry_points.txt
alacorder-81.2.26.dist-info/RECORD
