Metadata-Version: 2.1
Name: alacorder
Version: 81.2.26
Summary: Alacorder retrieves case detail PDFs from Alacourt.com and processes them into data tables suitable for research purposes.
Author: Sam Robson
Author-email: sbrobson@crimson.ua.edu
Requires-Python: >=3.10,<4.0
Classifier: Programming Language :: Python :: 3
Classifier: Programming Language :: Python :: 3.10
Classifier: Programming Language :: Python :: 3.11
Requires-Dist: brotli (>=1.1.0,<2.0.0)
Requires-Dist: bs4 (>=0.0.1,<0.0.2)
Requires-Dist: docxtpl (>=0.16.7,<0.17.0)
Requires-Dist: polars (>=0.20.15,<0.21.0)
Requires-Dist: pymupdf (>=1.22.5,<2.0.0)
Requires-Dist: rich (>=13.5.2,<14.0.0)
Requires-Dist: selenium (>=4.10.0,<5.0.0)
Requires-Dist: textual (>=0.40.0,<0.41.0)
Requires-Dist: typer[all] (>=0.9.0,<0.10.0)
Requires-Dist: xlsx2csv (>=0.8.1,<0.9.0)
Requires-Dist: xlsxwriter (>=3.1.2,<4.0.0)
